shadow/__init__.py
shadow/context.py
shadow/log.py
shadow/run_server.py
shadow/start.py
shadow/protocols/Fast.py
shadow/protocols/NATTraversal.py
shadow/protocols/SC.py
shadow/protocols/SCS.py
shadow/protocols/__init__.py
shadow/protocols/baseProtocol.py
shadow/protocols/port_forward.py
shadow/protocols/sock5.py
shadow/unit/__init__.py
shadow/unit/conf_schema.py
shadow/unit/config_decode.py
shadow/unit/crypto_tools.py
shadow/unit/misc.py
shadowChain-0.0.3.dist-info/DESCRIPTION.rst
shadowChain-0.0.3.dist-info/METADATA
shadowChain-0.0.3.dist-info/RECORD
shadowChain-0.0.3.dist-info/WHEEL
shadowChain-0.0.3.dist-info/entry_points.txt
shadowChain-0.0.3.dist-info/metadata.json
shadowChain-0.0.3.dist-info/top_level.txt
