Metadata-Version: 2.0
Name: shadowChain
Version: 0.0.3
Summary: A proxy tool
Home-page: https://github.com/zh-explorer/shadowChain
Author: explorer
Author-email: hsadkhk@gmail.com
License: Apache License 2.0
Keywords: proxy
Platform: UNKNOWN
Classifier: Development Status :: 3 - Alpha
Classifier: Intended Audience :: Customer Service
Classifier: License :: OSI Approved :: Apache Software License
Classifier: Programming Language :: Python :: 3.5
Classifier: Programming Language :: Python :: 3.6
Requires-Dist: jsonschema (>=2.3.0)
Requires-Dist: pycryptodome (>=3.6)
